ksrg/__init__.py
ksrg/ksrgapi.py
ksrg-0.1.0.dist-info/LICENSE
ksrg-0.1.0.dist-info/METADATA
ksrg-0.1.0.dist-info/WHEEL
ksrg-0.1.0.dist-info/top_level.txt
ksrg-0.1.0.dist-info/RECORD
